README.rst
_description.org
lh-agpl3-LICENSE.txt
pyproject.toml
setup.py
bin/regFpsExample.cs
bisos/__init__.py
bisos.regfps.egg-info/PKG-INFO
bisos.regfps.egg-info/SOURCES.txt
bisos.regfps.egg-info/dependency_links.txt
bisos.regfps.egg-info/not-zip-safe
bisos.regfps.egg-info/requires.txt
bisos.regfps.egg-info/top_level.txt
bisos/regfps/__init__.py
bisos/regfps/regfps.py
bisos/regfps/regfpsPkgThis.py